tronlastpy/__init__.py
tronlastpy/main.py
tronlastpy-0.0.1.dist-info/licenses/LICENSE.txt
tronlastpy-0.0.1.dist-info/METADATA
tronlastpy-0.0.1.dist-info/WHEEL
tronlastpy-0.0.1.dist-info/top_level.txt
tronlastpy-0.0.1.dist-info/RECORD
